{
  "openapi": "3.0.4",
  "info": {
    "title": "ImageAPI",
    "version": "1.0"
  },
  "paths": {
    "/api/Image/upload-request": {
      "post": {
        "tags": [
          "Image"
        ],
        "requestBody": {
          "content": {
            "application/json": {
              "schema": {
                "$ref": "#/components/schemas/ImageMetadataDto"
              }
            },
            "text/json": {
              "schema": {
                "$ref": "#/components/schemas/ImageMetadataDto"
              }
            },
            "application/*+json": {
              "schema": {
                "$ref": "#/components/schemas/ImageMetadataDto"
              }
            }
          }
        },
        "responses": {
          "200": {
            "description": "OK",
            "content": {
              "text/plain": {
                "schema": {
                  "$ref": "#/components/schemas/ResponseDto"
                }
              },
              "application/json": {
                "schema": {
                  "$ref": "#/components/schemas/ResponseDto"
                }
              },
              "text/json": {
                "schema": {
                  "$ref": "#/components/schemas/ResponseDto"
                }
              }
            }
          }
        }
      }
    },
    "/api/Image/get-images-by-user": {
      "get": {
        "tags": [
          "Image"
        ],
        "responses": {
          "200": {
            "description": "OK",
            "content": {
              "text/plain": {
                "schema": {
                  "$ref": "#/components/schemas/ResponseDto"
                }
              },
              "application/json": {
                "schema": {
                  "$ref": "#/components/schemas/ResponseDto"
                }
              },
              "text/json": {
                "schema": {
                  "$ref": "#/components/schemas/ResponseDto"
                }
              }
            }
          }
        }
      }
    },
    "/api/Image/get-images": {
      "get": {
        "tags": [
          "Image"
        ],
        "responses": {
          "200": {
            "description": "OK",
            "content": {
              "text/plain": {
                "schema": {
                  "$ref": "#/components/schemas/ResponseDto"
                }
              },
              "application/json": {
                "schema": {
                  "$ref": "#/components/schemas/ResponseDto"
                }
              },
              "text/json": {
                "schema": {
                  "$ref": "#/components/schemas/ResponseDto"
                }
              }
            }
          }
        }
      }
    },
    "/api/Image/update-thumbnail-status": {
      "put": {
        "tags": [
          "Image"
        ],
        "requestBody": {
          "content": {
            "application/json": {
              "schema": {
                "$ref": "#/components/schemas/ImageMetadataDto"
              }
            },
            "text/json": {
              "schema": {
                "$ref": "#/components/schemas/ImageMetadataDto"
              }
            },
            "application/*+json": {
              "schema": {
                "$ref": "#/components/schemas/ImageMetadataDto"
              }
            }
          }
        },
        "responses": {
          "200": {
            "description": "OK",
            "content": {
              "text/plain": {
                "schema": {
                  "$ref": "#/components/schemas/ResponseDto"
                }
              },
              "application/json": {
                "schema": {
                  "$ref": "#/components/schemas/ResponseDto"
                }
              },
              "text/json": {
                "schema": {
                  "$ref": "#/components/schemas/ResponseDto"
                }
              }
            }
          }
        }
      }
    }
  },
  "components": {
    "schemas": {
      "ImageMetadataDto": {
        "required": [
          "contentType"
        ],
        "type": "object",
        "properties": {
          "id": {
            "type": "string",
            "format": "uuid"
          },
          "fileName": {
            "type": "string",
            "nullable": true
          },
          "fileSize": {
            "type": "integer",
            "format": "int64"
          },
          "uploadDate": {
            "type": "string",
            "format": "date-time"
          },
          "status": {
            "type": "string",
            "nullable": true
          },
          "thumbnailUrl": {
            "type": "string",
            "nullable": true
          },
          "userId": {
            "type": "string",
            "nullable": true
          },
          "contentType": {
            "minLength": 1,
            "type": "string"
          },
          "gcsObjectName": {
            "type": "string",
            "nullable": true
          }
        },
        "additionalProperties": false
      },
      "ResponseDto": {
        "type": "object",
        "properties": {
          "result": {
            "nullable": true
          },
          "isSuccess": {
            "type": "boolean"
          },
          "message": {
            "type": "string",
            "nullable": true
          }
        },
        "additionalProperties": false
      }
    }
  }
}